INSTALL.rst
LICENSE
MANIFEST.in
README.rst
VERSION
requirements.txt
setup.py
tasks.py
src/jarvis_pentest.egg-info/PKG-INFO
src/jarvis_pentest.egg-info/SOURCES.txt
src/jarvis_pentest.egg-info/dependency_links.txt
src/jarvis_pentest.egg-info/entry_points.txt
src/jarvis_pentest.egg-info/not-zip-safe
src/jarvis_pentest.egg-info/requires.txt
src/jarvis_pentest.egg-info/top_level.txt
src/pentest/__init__.py
src/pentest/__main__.py
src/pentest/__meta__.py
src/pentest/command.py
src/pentest/manager.py
src/pentest/parser.py
src/pentest/utils.py
src/pentest/hooks/__init__.py
src/pentest/hooks/airodump.py
src/pentest/hooks/amass.py
src/pentest/hooks/arpscan.py
src/pentest/hooks/crackmapexec.py
src/pentest/hooks/curl.py
src/pentest/hooks/dnsmap.py
src/pentest/hooks/dnsrecon.py
src/pentest/hooks/hping3.py
src/pentest/hooks/http.py
src/pentest/hooks/hydra.py
src/pentest/hooks/iscsiadm.py
src/pentest/hooks/keimpx.py
src/pentest/hooks/ldapsearch.py
src/pentest/hooks/ldeep.py
src/pentest/hooks/msfconsole.py
src/pentest/hooks/nbtscan.py
src/pentest/hooks/nikto.py
src/pentest/hooks/nmap.py
src/pentest/hooks/nmblookup.py
src/pentest/hooks/patator.py
src/pentest/hooks/pywerview.py
src/pentest/hooks/rpcclient.py
src/pentest/hooks/showmount.py
src/pentest/hooks/skipfish.py
src/pentest/hooks/smbclient.py
src/pentest/hooks/smbmap.py
src/pentest/hooks/sslyze.py
src/pentest/hooks/teRMInator.py
src/pentest/hooks/tshark.py
src/pentest/hooks/wfuzz.py
src/pentest/tests/__init__.py
src/pentest/tests/__main__.py
src/pentest/tests/test_documentation.py
src/pentest/tests/test_jarvis.py