Metadata-Version: 1.2
Name: jarvis-pentest
Version: 1.0.0
Summary: The pentest companion
Home-page: https://github.com/BastienFaure/jarvis
Author: b0z
Author-email: bastien@faure.io
License: MIT
Platform: any
Classifier: Development Status :: 4 - Beta
Classifier: Intended Audience :: Information Technology
Classifier: License :: OSI Approved :: MIT License
Classifier: Operating System :: POSIX :: Linux
Classifier: Programming Language :: Python
Classifier: Programming Language :: Python :: 3.3
Classifier: Programming Language :: Python :: 3 :: Only
Classifier: Topic :: Software Development :: Libraries
Requires-Python: >=3.3
